tp_apm/__init__.py
tp_apm/tp_apm.py
tp_apm-0.0.4.dist-info/LICENSE
tp_apm-0.0.4.dist-info/METADATA
tp_apm-0.0.4.dist-info/WHEEL
tp_apm-0.0.4.dist-info/top_level.txt
tp_apm-0.0.4.dist-info/RECORD
